power_ranker/__init__.py
power_ranker/colley.py
power_ranker/exception.py
power_ranker/get_season_data.py
power_ranker/history.py
power_ranker/league.py
power_ranker/lsq.py
power_ranker/playoff_odds.py
power_ranker/private.py
power_ranker/settings.py
power_ranker/two_step_dom.py
power_ranker/utils.py
power_ranker/docs/ConfigurationDocumentation.md
power_ranker/docs/PublishingWebsite.md
power_ranker/docs/default_config.cfg
power_ranker/docs/template/about.html
power_ranker/docs/template/about.js
power_ranker/docs/template/cover.css
power_ranker/docs/template/dom_graph.png
power_ranker/docs/template/history.html
power_ranker/docs/template/history.js
power_ranker/docs/template/player.html
power_ranker/docs/template/power.html
power_ranker/docs/template/theme.css
power_ranker/docs/template/theme.js
power_ranker/docs/template/tiers_example.png
power_ranker/docs/template/welcome.html
power_ranker/docs/template/assets/brand/bootstrap-outline.svg
power_ranker/docs/template/assets/brand/bootstrap-punchout.svg
power_ranker/docs/template/assets/brand/bootstrap-solid.svg
power_ranker/docs/template/assets/css/docs.min.css
power_ranker/docs/template/assets/css/docs.min.css.map
power_ranker/docs/template/assets/css/ie10-viewport-bug-workaround.css
power_ranker/docs/template/assets/css/src/docs.css
power_ranker/docs/template/assets/css/src/pygments-manni.css
power_ranker/docs/template/assets/flash/ZeroClipboard.swf
power_ranker/docs/template/assets/img/components.png
power_ranker/docs/template/assets/img/devices.png
power_ranker/docs/template/assets/img/expo-lyft.jpg
power_ranker/docs/template/assets/img/expo-newsweek.jpg
power_ranker/docs/template/assets/img/expo-riot.jpg
power_ranker/docs/template/assets/img/expo-vogue.jpg
power_ranker/docs/template/assets/img/sass-less.png
power_ranker/docs/template/assets/js/customize.min.js
power_ranker/docs/template/assets/js/docs.min.js
power_ranker/docs/template/assets/js/ie-emulation-modes-warning.js
power_ranker-2.1.0.dist-info/LICENSE
power_ranker-2.1.0.dist-info/METADATA
power_ranker-2.1.0.dist-info/WHEEL
power_ranker-2.1.0.dist-info/entry_points.txt
power_ranker-2.1.0.dist-info/top_level.txt
power_ranker-2.1.0.dist-info/RECORD
