Metadata-Version: 2.1
Name: power-ranker
Version: 2.1.0
Summary: Fantasy football power rankings for public ESPN leagues
Home-page: http://github.com/rynecarbone/power_ranker
Author: Ryne Carbone
Author-email: ryne.carbone@gmail.com
License: MIT
Platform: UNKNOWN
Classifier: Development Status :: 4 - Beta
Classifier: License :: OSI Approved :: MIT License
Classifier: Natural Language :: English
Classifier: Operating System :: OS Independent
Classifier: Programming Language :: Python :: 3.6
Requires-Python: >=3.6
Requires-Dist: bs4
Requires-Dist: configparser
Requires-Dist: lxml
Requires-Dist: matplotlib
Requires-Dist: numpy
Requires-Dist: pandas
Requires-Dist: requests
Requires-Dist: scipy
Requires-Dist: plotnine
